pybel_git/__init__.py
pybel_git/__main__.py
pybel_git/cli.py
pybel_git/git.py
pybel_git/gitlab.py
pybel_git-0.1.0.dist-info/LICENSE
pybel_git-0.1.0.dist-info/METADATA
pybel_git-0.1.0.dist-info/WHEEL
pybel_git-0.1.0.dist-info/entry_points.txt
pybel_git-0.1.0.dist-info/top_level.txt
pybel_git-0.1.0.dist-info/RECORD
