Metadata-Version: 2.1
Name: pybel-git
Version: 0.1.0
Summary: PyBEL Git utilities
Home-page: https://github.com/pybel/pybel-git
Author: Charles Tapley Hoyt
Author-email: cthoyt@gmail.com
Maintainer: Charles Tapley Hoyt
Maintainer-email: cthoyt@gmail.com
License: MIT
Download-URL: https://github.com/pybel/pybel-git/releases
Project-URL: Bug Tracker, https://github.com/pybel/pybel-git/issues
Project-URL: Source Code, https://github.com/pybel/pybel-git
Keywords: Biological Expression Language,Protein Protein Interaction Networks
Platform: UNKNOWN
Classifier: Development Status :: 1 - Planning
Classifier: Intended Audience :: Developers
Classifier: Programming Language :: Python
Classifier: Programming Language :: Python :: 3.7
Classifier: Programming Language :: Python :: 3.6
Classifier: Programming Language :: Python :: 3 :: Only
Classifier: License :: OSI Approved :: MIT License
Requires-Python: >=3.6
Requires-Dist: pybel (>=0.14.0)
Requires-Dist: click
Requires-Dist: easy-config
Requires-Dist: gitpython
